compound_data/__init__.py
compound_data/pair.py
compound_data-0.1.dist-info/METADATA
compound_data-0.1.dist-info/WHEEL
compound_data-0.1.dist-info/top_level.txt
compound_data-0.1.dist-info/RECORD
