Metadata-Version: 2.1
Name: compound-data
Version: 0.1
Summary: New Data Type - Pair
Home-page: https://github.com/xaliion/python-type
Author: Xalion
Author-email: UNKNOWN
License: MIT
Platform: UNKNOWN
